openclsim/__init__.py
openclsim/io.py
openclsim/utils.py
openclsim/core/__init__.py
openclsim/core/container.py
openclsim/core/events_container.py
openclsim/core/identifiable.py
openclsim/core/locatable.py
openclsim/core/log.py
openclsim/core/movable.py
openclsim/core/processor.py
openclsim/core/resource.py
openclsim/core/simpy_object.py
openclsim/critical_path/__init__.py
openclsim/critical_path/base_cp.py
openclsim/critical_path/dependencies_from_model.py
openclsim/critical_path/dependencies_from_recorded_activities.py
openclsim/critical_path/dependencies_from_simpy_step.py
openclsim/critical_path/simulation_graph.py
openclsim/model/__init__.py
openclsim/model/base_activities.py
openclsim/model/basic_activity.py
openclsim/model/helpers.py
openclsim/model/move_activity.py
openclsim/model/parallel_activity.py
openclsim/model/sequential_activity.py
openclsim/model/shift_amount_activity.py
openclsim/model/single_run_process.py
openclsim/model/while_activity.py
openclsim/plot/__init__.py
openclsim/plot/log_dataframe.py
openclsim/plot/step_chart.py
openclsim/plot/vessel_planning.py
openclsim/plugins/__init__.py
openclsim/plugins/delay.py
openclsim/plugins/weather.py
openclsim-1.6.3.dist-info/licenses/AUTHORS.rst
openclsim-1.6.3.dist-info/licenses/LICENSE.txt
openclsim-1.6.3.dist-info/METADATA
openclsim-1.6.3.dist-info/WHEEL
openclsim-1.6.3.dist-info/top_level.txt
openclsim-1.6.3.dist-info/RECORD
