Metadata-Version: 2.4
Name: openclsim
Version: 1.6.3
Summary: The OpenCLSim package aims to facilitate rule based planning of cyclic activities and in depth comparison of different system concepts.
Home-page: https://github.com/TUDelft-CITG/openclsim
Author: "Mark van Koningsveld",
Author-email: "m.vankoningsveld@tudelft.nl",
License: MIT
Keywords: OpenCLSim
Classifier: Development Status :: 4 - Beta
Classifier: Programming Language :: Python
License-File: LICENSE.txt
License-File: AUTHORS.rst
Requires-Dist: setuptools>=61
Requires-Dist: importlib-metadata; python_version < "3.8"
Requires-Dist: setuptools_scm[toml]>=5
Requires-Dist: pandas>=0.24.0
Requires-Dist: numpy
Requires-Dist: networkx
Requires-Dist: simpy
Requires-Dist: shapely>=2
Requires-Dist: pyproj
Requires-Dist: plotly
Requires-Dist: matplotlib
Requires-Dist: networkx
Requires-Dist: Deprecated
Provides-Extra: testing
Requires-Dist: black; extra == "testing"
Requires-Dist: coverage-badge; extra == "testing"
Requires-Dist: contextily; extra == "testing"
Requires-Dist: faker; extra == "testing"
Requires-Dist: flake8<5; extra == "testing"
Requires-Dist: folium; extra == "testing"
Requires-Dist: ipywidgets>=7; extra == "testing"
Requires-Dist: jupyter-book>=0.13.1; extra == "testing"
Requires-Dist: jupyter>=1.0.0; extra == "testing"
Requires-Dist: lxml; extra == "testing"
Requires-Dist: mock; extra == "testing"
Requires-Dist: mypy; extra == "testing"
Requires-Dist: nbmake; extra == "testing"
Requires-Dist: nose; extra == "testing"
Requires-Dist: notebook>=6.4.12; extra == "testing"
Requires-Dist: opentnsim; extra == "testing"
Requires-Dist: pyarrow; extra == "testing"
Requires-Dist: plotly; extra == "testing"
Requires-Dist: pylama; extra == "testing"
Requires-Dist: pylama_pylint; extra == "testing"
Requires-Dist: pytest; extra == "testing"
Requires-Dist: pytest-black; extra == "testing"
Requires-Dist: pytest-cov; extra == "testing"
Requires-Dist: pytest-datadir; extra == "testing"
Requires-Dist: pytest-flake8; extra == "testing"
Requires-Dist: pytest-isort; extra == "testing"
Requires-Dist: pytest-logging; extra == "testing"
Requires-Dist: pytest-mock; extra == "testing"
Requires-Dist: pytest-mypy; extra == "testing"
Requires-Dist: pytest-runner; extra == "testing"
Requires-Dist: pytest-split; extra == "testing"
Requires-Dist: pytest-timeout; extra == "testing"
Requires-Dist: simplekml; extra == "testing"
Provides-Extra: docs
Requires-Dist: sphinx>=1.8.0; extra == "docs"
Requires-Dist: sphinx_rtd_theme; extra == "docs"
Dynamic: license-file
